blue_objects/__init__.py
blue_objects/__main__.py
blue_objects/config.env
blue_objects/env.py
blue_objects/markdown.py
blue_objects/objects.py
blue_objects/path.py
blue_objects/sample.env
blue_objects/urls.py
blue_objects/.abcli/abcli.sh
blue_objects/.abcli/actions.sh
blue_objects/.abcli/aka.sh
blue_objects/.abcli/alias.sh
blue_objects/.abcli/blue_objects.sh
blue_objects/.abcli/cache.sh
blue_objects/.abcli/clone.sh
blue_objects/.abcli/download.sh
blue_objects/.abcli/file.sh
blue_objects/.abcli/gif.sh
blue_objects/.abcli/host.sh
blue_objects/.abcli/ls.sh
blue_objects/.abcli/metadata.sh
blue_objects/.abcli/mlflow.sh
blue_objects/.abcli/mysql.sh
blue_objects/.abcli/object.sh
blue_objects/.abcli/publish.sh
blue_objects/.abcli/select.sh
blue_objects/.abcli/storage.sh
blue_objects/.abcli/tags.sh
blue_objects/.abcli/upload.sh
blue_objects/.abcli/metadata/get.sh
blue_objects/.abcli/metadata/post.sh
blue_objects/.abcli/mlflow/browse.sh
blue_objects/.abcli/mlflow/cache.sh
blue_objects/.abcli/mlflow/list_registered_models.sh
blue_objects/.abcli/mlflow/log_artifacts.sh
blue_objects/.abcli/mlflow/log_run.sh
blue_objects/.abcli/mlflow/run.sh
blue_objects/.abcli/mlflow/tags.sh
blue_objects/.abcli/mlflow/test.sh
blue_objects/.abcli/mlflow/transition.sh
blue_objects/.abcli/mlflow/tags/clone.sh
blue_objects/.abcli/mlflow/tags/get.sh
blue_objects/.abcli/mlflow/tags/search.sh
blue_objects/.abcli/mlflow/tags/set.sh
blue_objects/.abcli/mysql/cache.sh
blue_objects/.abcli/mysql/relations.sh
blue_objects/.abcli/mysql/tags.sh
blue_objects/.abcli/storage/clear.sh
blue_objects/.abcli/storage/download_file.sh
blue_objects/.abcli/storage/exists.sh
blue_objects/.abcli/storage/list.sh
blue_objects/.abcli/storage/rm.sh
blue_objects/.abcli/storage/status.sh
blue_objects/.abcli/tests/README.sh
blue_objects/.abcli/tests/clone.sh
blue_objects/.abcli/tests/help.sh
blue_objects/.abcli/tests/host.sh
blue_objects/.abcli/tests/ls.sh
blue_objects/.abcli/tests/metadata.sh
blue_objects-5.340.1.dist-info/licenses/LICENSE
blue_objects-5.340.1.dist-info/METADATA
blue_objects-5.340.1.dist-info/WHEEL
blue_objects-5.340.1.dist-info/top_level.txt
blue_objects-5.340.1.dist-info/RECORD
