Metadata-Version: 2.4
Name: blue_objects
Version: 5.340.1
Summary: 🌀 data objects for Bash.
Home-page: https://github.com/kamangir/blue-objects
Author: Arash Abadpour (Kamangir)
Author-email: arash@kamangir.net
License: Public Domain
Classifier: Programming Language :: Python :: 3
Classifier: Programming Language :: Unix Shell
Classifier: License :: Public Domain
Classifier: Operating System :: OS Independent
License-File: LICENSE
Requires-Dist: abcli
Requires-Dist: dill
Requires-Dist: mlflow
Requires-Dist: pandas
Requires-Dist: urllib3
Provides-Extra: opencv
Requires-Dist: opencv-python; extra == "opencv"
Dynamic: author
Dynamic: author-email
Dynamic: classifier
Dynamic: description
Dynamic: description-content-type
Dynamic: home-page
Dynamic: license
Dynamic: license-file
Dynamic: provides-extra
Dynamic: requires-dist
Dynamic: summary
